Metadata-Version: 1.0
Name: krestiki-noliki
Version: 0.1.0
Summary: Game krestiki_noliki.for play write "krestiki_noliki --start" in console
Home-page: UNKNOWN
Author: UNKNOWN
Author-email: UNKNOWN
License: UNKNOWN
Platform: UNKNOWN
